[
    {
        "category": "Science & Nature",
        "correct_answer": "Blue",
        "difficulty": "hard",
        "incorrect_answers_uno": "Red",
        "incorrect_answers_due": "Green",
        "incorrect_answers_tre": "Purple",
        "question": "What is considered the rarist form of color blindness?",
        "type": "multiple"
    },
    {
        "category": "Mythology",
        "correct_answer": "Athena",
        "difficulty": "medium",
        "incorrect_answers_uno": "Ares",
        "incorrect_answers_due": "Artemis",
        "incorrect_answers_tre": "Apollo",
        "question": "This Greek mythological figure is the god/goddess of battle strategy (among other things).",
        "type": "multiple"
    },
    {
        "category": "Science: Computers",
        "correct_answer": "Central Processing Unit",
        "difficulty": "easy",
        "incorrect_answers_uno": "Central Process Unit",
        "incorrect_answers_due": "Computer Personal Unit",
        "incorrect_answers_tre": "Central Processor Unit",
        "question": "What does CPU stand for?",
        "type": "multiple"
    },
    {
        "category": "Entertainment: Books",
        "correct_answer": "Frankenstein",
        "difficulty": "easy",
        "incorrect_answers_uno": "Dracula",
        "incorrect_answers_due": "The Strange Case of Dr. Jekyll and Mr. Hyde ",
        "incorrect_answers_tre": "The Legend of Sleepy Hollow",
        "question": "Which famous book is sub-titled &#039;The Modern Prometheus&#039;?",
        "type": "multiple"
    },
    {
        "category": "Science: Computers",
        "correct_answer": "Think",
        "difficulty": "medium",
        "incorrect_answers_uno": "Click",
        "incorrect_answers_due": "Logic",
        "incorrect_answers_tre": "Pixel",
        "question": "What five letter word is the motto of the IBM Computer company?",
        "type": "multiple"
    },
    {
        "category": "Entertainment: Books",
        "correct_answer": "Seeker",
        "difficulty": "medium",
        "incorrect_answers_uno": "Beater",
        "incorrect_answers_due": "Chaser",
        "incorrect_answers_tre": "Keeper",
        "question": "What position does Harry Potter play in Quidditch?",
        "type": "multiple"
    },
    {
        "category": "Science & Nature",
        "correct_answer": "Nitrogen",
        "difficulty": "easy",
        "incorrect_answers_uno": "Oxygen",
        "incorrect_answers_due": "Argon",
        "incorrect_answers_tre": "Carbon Dioxide",
        "question": "Which gas forms about 78% of the Earth&rsquo;s atmosphere?",
        "type": "multiple"
    },
    {
        "category": "General Knowledge",
        "correct_answer": "Wasabi ",
        "difficulty": "medium",
        "incorrect_answers_uno": "Mentsuyu",
        "incorrect_answers_due": "Karashi",
        "incorrect_answers_tre": "Ponzu",
        "question": "Which essential condiment is also known as Japanese horseradish?",
        "type": "multiple"
    },
    {
        "category": "Entertainment: Music",
        "correct_answer": "Hurry Up, We&#039;re Dreaming",
        "difficulty": "hard",
        "incorrect_answers_uno": "Saturdays = Youth",
        "incorrect_answers_due": "Before the Dawn Heals Us",
        "incorrect_answers_tre": "Junk",
        "question": "Which M83 album is the song &quot;Midnight City&quot; featured in?",
        "type": "multiple"
    },
    {
        "category": "History",
        "correct_answer": "Sumerian",
        "difficulty": "medium",
        "incorrect_answers_uno": "Maltese",
        "incorrect_answers_due": "Akkadian",
        "incorrect_answers_tre": "Mandaic",
        "question": "Which of the following is NOT classified as a Semetic language?",
        "type": "multiple"
    },
    {
        "category": "Science: Computers",
        "correct_answer": "Santa Clara",
        "difficulty": "medium",
        "incorrect_answers_uno": "Palo Alto",
        "incorrect_answers_due": "Cupertino",
        "incorrect_answers_tre": "Mountain View",
        "question": "Nvidia&#039;s headquarters are based in which Silicon Valley city?",
        "type": "multiple"
    },
    {
        "category": "Entertainment: Video Games",
        "correct_answer": "A potato",
        "difficulty": "medium",
        "incorrect_answers_uno": "A tomato",
        "incorrect_answers_due": "A lemon",
        "incorrect_answers_tre": "An apple",
        "question": "In Portal 2, the iconic character GLaDOS is turned into:",
        "type": "multiple"
    },
    {
        "category": "Entertainment: Video Games",
        "correct_answer": "Magnus P&aring;lsson",
        "difficulty": "medium",
        "incorrect_answers_uno": "Terry Cavanagh",
        "incorrect_answers_due": "Danny Baranowsky",
        "incorrect_answers_tre": "Joel Zimmerman",
        "question": "Who composed the soundtrack for the game VVVVVV?",
        "type": "multiple"
    },
    {
        "category": "Entertainment: Cartoon & Animations",
        "correct_answer": "Scud",
        "difficulty": "medium",
        "incorrect_answers_uno": "Buster",
        "incorrect_answers_due": "Whiskers",
        "incorrect_answers_tre": "Mr. Jones",
        "question": "What is the name of Sid&#039;s dog in &quot;Toy Story&quot;?",
        "type": "multiple"
    },
    {
        "category": "Vehicles",
        "correct_answer": "TCAS",
        "difficulty": "easy",
        "incorrect_answers_uno": "GPWS",
        "incorrect_answers_due": "OCAS",
        "incorrect_answers_tre": "TAWS",
        "question": "Which of the following collision avoidance systems helps airplanes avoid colliding with each other?",
        "type": "multiple"
    },
    {
        "category": "Science & Nature",
        "correct_answer": "Eyes",
        "difficulty": "medium",
        "incorrect_answers_uno": "Throat",
        "incorrect_answers_due": "Stomach",
        "incorrect_answers_tre": "Blood",
        "question": "Which part of the body does glaucoma affect?",
        "type": "multiple"
    },
    {
        "category": "General Knowledge",
        "correct_answer": "Big Mouth Billy Bass",
        "difficulty": "medium",
        "incorrect_answers_uno": "Big Billy Bass",
        "incorrect_answers_due": "Singing Fish",
        "incorrect_answers_tre": "Sardeen",
        "question": "What is the name of the popular animatronic singing fish prop, singing such hits such as &quot;Don&#039;t Worry, Be Happy&quot;?",
        "type": "multiple"
    },
    {
        "category": "Entertainment: Musicals & Theatres",
        "correct_answer": "The Elves",
        "difficulty": "hard",
        "incorrect_answers_uno": "Wicked",
        "incorrect_answers_due": "Hamilton",
        "incorrect_answers_tre": "The Book of Mormon",
        "question": "What is the name of Broadway&#039;s first &quot;long-run&quot; musical?",
        "type": "multiple"
    },
    {
        "category": "Entertainment: Music",
        "correct_answer": "Rain Man",
        "difficulty": "medium",
        "incorrect_answers_uno": "Without Me",
        "incorrect_answers_due": "Kim",
        "incorrect_answers_tre": "Square Dance",
        "question": "Which of these songs by artist Eminem contain the lyric &quot;Nice to meet you. Hi, my name is... I forgot my name!&quot;?",
        "type": "multiple"
    },
    {
        "category": "Entertainment: Film",
        "correct_answer": "Men of Harlech",
        "difficulty": "hard",
        "incorrect_answers_uno": "Scotland the Brave",
        "incorrect_answers_due": "Colonel Bogey March",
        "incorrect_answers_tre": "The British Grenadiers",
        "question": "In the 1964 film  what song does the British Army company sing before the final battle?",
        "type": "multiple"
    },
    {
        "category": "Geography",
        "correct_answer": "Dzongkha",
        "difficulty": "medium",
        "incorrect_answers_uno": "Ladakhi",
        "incorrect_answers_due": "Karen",
        "incorrect_answers_tre": "Groma",
        "question": "What is the official language of Bhutan?",
        "type": "multiple"
    },
    {
        "category": "Entertainment: Video Games",
        "correct_answer": "Half Life 2",
        "difficulty": "medium",
        "incorrect_answers_uno": "Team Fortress 2",
        "incorrect_answers_due": "Dark Souls",
        "incorrect_answers_tre": "Serious Sam: The Second Encounter",
        "question": "In which game does a character say, &quot;Sometimes, I dream about cheese&quot;?",
        "type": "multiple"
    },
    {
        "category": "Science: Computers",
        "correct_answer": "Assembly",
        "difficulty": "medium",
        "incorrect_answers_uno": "Python",
        "incorrect_answers_due": "C#",
        "incorrect_answers_tre": "Pascal",
        "question": "Which of these programming languages is a low-level language?",
        "type": "multiple"
    },
    {
        "category": "Entertainment: Video Games",
        "correct_answer": "San Andreas",
        "difficulty": "medium",
        "incorrect_answers_uno": "San Fierro",
        "incorrect_answers_due": "Las Venturas",
        "incorrect_answers_tre": "Vice City",
        "question": "Which of these is not the name of a city in the Grand Theft Auto series?",
        "type": "multiple"
    },
    {
        "category": "Entertainment: Video Games",
        "correct_answer": "Ultimate Swimmer",
        "difficulty": "hard",
        "incorrect_answers_uno": "Ultimate Detective",
        "incorrect_answers_due": "Ultimate Gambler",
        "incorrect_answers_tre": "Ultimate Dancer",
        "question": "In the game Danganronpa: Happy Trigger Havoc, the character Aoi Asahina&#039;s ultimate ability is what?",
        "type": "multiple"
    },
    {
        "category": "Celebrities",
        "correct_answer": "The Party",
        "difficulty": "medium",
        "incorrect_answers_uno": "The Weather Girls",
        "incorrect_answers_due": "The Pussycat Dolls",
        "incorrect_answers_tre": "The Cheetah Girls",
        "question": "Before voicing Pearl in Steven Universe, Deedee Magno Hall was part of which American band?",
        "type": "multiple"
    },
    {
        "category": "Entertainment: Music",
        "correct_answer": "Jamie Foxx",
        "difficulty": "easy",
        "incorrect_answers_uno": "Alec Baldwin",
        "incorrect_answers_due": "Dwayne Johnson",
        "incorrect_answers_tre": " Bruce Willis",
        "question": "Kanye West&#039;s &quot;Gold Digger&quot; featured which Oscar-winning actor?",
        "type": "multiple"
    },
    {
        "category": "Science: Computers",
        "correct_answer": "NovodeX",
        "difficulty": "hard",
        "incorrect_answers_uno": "Ageia",
        "incorrect_answers_due": "Nvidia",
        "incorrect_answers_tre": "AMD",
        "question": "Who is the original author of the realtime physics engine called PhysX?",
        "type": "multiple"
    },
    {
        "category": "Science: Computers",
        "correct_answer": "FM-7",
        "difficulty": "medium",
        "incorrect_answers_uno": "PC-9801",
        "incorrect_answers_due": "Xmillennium ",
        "incorrect_answers_tre": "MSX",
        "question": "Which of the following is a personal computer made by the Japanese company Fujitsu?",
        "type": "multiple"
    },
    {
        "category": "Entertainment: Video Games",
        "correct_answer": "Dragon King: The Fighting Game",
        "difficulty": "hard",
        "incorrect_answers_uno": "Nintendo Legends: Fight!",
        "incorrect_answers_due": "Martial Arts: King of the Hill",
        "incorrect_answers_tre": "Aerial Warriors: Supreme Battle",
        "question": "What was the name of the game created by Masahiro Sakurai and Satoru Iwata that would eventually evolve into &quot;Super Smash Bros.&quot;?",
        "type": "multiple"
    },
    {
        "category": "General Knowledge",
        "correct_answer": "Polska",
        "difficulty": "easy",
        "incorrect_answers_uno": "Pupcia",
        "incorrect_answers_due": "Polszka",
        "incorrect_answers_tre": "P&oacute;land",
        "question": "What is the name of Poland in Polish?",
        "type": "multiple"
    },
    {
        "category": "Entertainment: Film",
        "correct_answer": "New York, New York",
        "difficulty": "medium",
        "incorrect_answers_uno": "Las Vegas, Nevada",
        "incorrect_answers_due": "Chicago, Illinois",
        "incorrect_answers_tre": "Orlando, Florida",
        "question": "What city did the monster attack in the film, &quot;Cloverfield&quot;?",
        "type": "multiple"
    },
    {
        "category": "History",
        "correct_answer": "The Polish President",
        "difficulty": "easy",
        "incorrect_answers_uno": "Pope John Paul II",
        "incorrect_answers_due": "Bang-Ding Ow",
        "incorrect_answers_tre": "Albert Putin",
        "question": "Who was among those killed in the 2010 Smolensk, Russia plane crash tragedy?",
        "type": "multiple"
    },
    {
        "category": "General Knowledge",
        "correct_answer": "Metropolitan Line",
        "difficulty": "easy",
        "incorrect_answers_uno": "Circle Line",
        "incorrect_answers_due": "Bakerloo Line",
        "incorrect_answers_tre": "Victoria Line",
        "question": "What was the first ever London Underground line to be built?",
        "type": "multiple"
    },
    {
        "category": "Entertainment: Music",
        "correct_answer": "2008",
        "difficulty": "medium",
        "incorrect_answers_uno": "2000",
        "incorrect_answers_due": "2015",
        "incorrect_answers_tre": "2004",
        "question": "In which year did &quot;Caravan Palace&quot; release their first album?",
        "type": "multiple"
    },
    {
        "category": "Science: Computers",
        "correct_answer": "2016",
        "difficulty": "medium",
        "incorrect_answers_uno": "2013",
        "incorrect_answers_due": "2009",
        "incorrect_answers_tre": "2011",
        "question": "When did the online streaming service &quot;Mixer&quot; launch?",
        "type": "multiple"
    },
    {
        "category": "Science: Computers",
        "correct_answer": "Non-impact printer",
        "difficulty": "medium",
        "incorrect_answers_uno": "Impact printer",
        "incorrect_answers_due": "Daisywheel printer",
        "incorrect_answers_tre": "Dot matrix printer",
        "question": "Laserjet and inkjet printers are both examples of what type of printer?",
        "type": "multiple"
    },
    {
        "category": "Entertainment: Video Games",
        "correct_answer": "Vanilla",
        "difficulty": "medium",
        "incorrect_answers_uno": "Peach",
        "incorrect_answers_due": "Strawberry",
        "incorrect_answers_tre": "Mint",
        "question": "What is the name of Cream the Rabbit&#039;s mom in the &quot;Sonic the Hedgehog&quot; series?",
        "type": "multiple"
    },
    {
        "category": "Science & Nature",
        "correct_answer": "The Sonoran Desert",
        "difficulty": "medium",
        "incorrect_answers_uno": "The Gobi Desert",
        "incorrect_answers_due": "The Yuma Desert",
        "incorrect_answers_tre": "The Arabian Desert",
        "question": "Which desert is the only desert in the world where the &quot;Saguaro&quot; cactus grows indigenously?",
        "type": "multiple"
    },
    {
        "category": "Science: Computers",
        "correct_answer": "Cheetah",
        "difficulty": "hard",
        "incorrect_answers_uno": "Puma",
        "incorrect_answers_due": "Tiger",
        "incorrect_answers_tre": "Leopard",
        "question": "Released in 2001, the first edition of Apple&#039;s Mac OS X operating system (version 10.0) was given what animal code name?",
        "type": "multiple"
    },
    {
        "category": "Entertainment: Film",
        "correct_answer": "Isla Nublar",
        "difficulty": "easy",
        "incorrect_answers_uno": "Isla Sorna",
        "incorrect_answers_due": "Isla Muerta",
        "incorrect_answers_tre": "Isla Pena",
        "question": "What is the name of the island that &quot;Jurassic Park&quot; is built on?",
        "type": "multiple"
    },
    {
        "category": "Entertainment: Video Games",
        "correct_answer": "Luigi",
        "difficulty": "medium",
        "incorrect_answers_uno": "Mr. Game &amp; Watch",
        "incorrect_answers_due": "Jigglypuff",
        "incorrect_answers_tre": "Pichu",
        "question": "Which of these is the only fighter in the game &quot;Super Smash Bros. Melee&quot; capable of dealing damage with their taunt animation?",
        "type": "multiple"
    },
    {
        "category": "General Knowledge",
        "correct_answer": "Sal Khan",
        "difficulty": "hard",
        "incorrect_answers_uno": "Ben Khan",
        "incorrect_answers_due": "Kitt Khan",
        "incorrect_answers_tre": "Adel Khan",
        "question": "Who founded the Khan Academy?",
        "type": "multiple"
    },
    {
        "category": "Entertainment: Video Games",
        "correct_answer": "Ed",
        "difficulty": "medium",
        "incorrect_answers_uno": "Charles",
        "incorrect_answers_due": "Lee",
        "incorrect_answers_tre": "Walter",
        "question": "In Telltale Games&#039; &quot;The Walking Dead: Season One&quot; what is the name of Clementine&#039;s father?",
        "type": "multiple"
    },
    {
        "category": "Entertainment: Television",
        "correct_answer": " Bryan Cranston",
        "difficulty": "easy",
        "incorrect_answers_uno": "Andrew Lincoln",
        "incorrect_answers_due": "Aaron Paul",
        "incorrect_answers_tre": "RJ Mitte",
        "question": "Which actor portrays &quot;Walter White&quot; in the series &quot;Breaking Bad&quot;?",
        "type": "multiple"
    },
    {
        "category": "Entertainment: Cartoon & Animations",
        "correct_answer": "33",
        "difficulty": "medium",
        "incorrect_answers_uno": "88",
        "incorrect_answers_due": "38",
        "incorrect_answers_tre": "83",
        "question": "What was the number on Gerald&#039;s shirt in &quot;Hey Arnold!&quot;?",
        "type": "multiple"
    },
    {
        "category": "Entertainment: Video Games",
        "correct_answer": "Donkey Kong",
        "difficulty": "hard",
        "incorrect_answers_uno": "Super Mario Bros.",
        "incorrect_answers_due": "Super Mario Land",
        "incorrect_answers_tre": "Mario Bros.",
        "question": "In which game did the character &quot;Mario&quot; make his first appearance?",
        "type": "multiple"
    },
    {
        "category": "Entertainment: Video Games",
        "correct_answer": "Call of Duty 3",
        "difficulty": "medium",
        "incorrect_answers_uno": "Call of Duty 4: Modern Warfare",
        "incorrect_answers_due": "Call of Duty: World at War",
        "incorrect_answers_tre": "Call of Duty: Roads to Victory",
        "question": "Which of the following Call of Duty games was a PS3 launch title?",
        "type": "multiple"
    },
    {
        "category": "Science & Nature",
        "correct_answer": "Eight",
        "difficulty": "hard",
        "incorrect_answers_uno": "Four",
        "incorrect_answers_due": "Two",
        "incorrect_answers_tre": "Six",
        "question": "How many protons are in an oxygen atom?",
        "type": "multiple"
    },
    {
        "category": "Geography",
        "correct_answer": "Nuuk",
        "difficulty": "medium",
        "incorrect_answers_uno": "Sisimiut",
        "incorrect_answers_due": "Narsaq",
        "incorrect_answers_tre": "Maniitsoq",
        "question": "What is the capital of Greenland?",
        "type": "multiple"
    }
]

